Workbook

Sheet Alta de Activo Fijo
A1: Alta de Activo Fijo (Valores) | F1: Según Tabla | G1: Se debe ingresar en el sistema la parametrización previa, asi el sistema podrá leer las siglas correctamente
F3: Para ingresar a la Importación se debe dirigir a Activo Fijo >> Operaciones >> Alta de Activo Fijo
G5: Dato Obligatorio
G6: Dato Posible
B8: 1 | C8: 2 | D8: 3 | E8: 4 | F8: 5 | G8: 6 | H8: 7
C9: Texto (3) | H9: Texto (3)
C10: Según Tabla | H10: Según Tabla
H12: 01: Muebles y Ut.
H13: 02: Instalaciones
H14: 03: Equipos
H15: 04: Rodados
H16: 05: Eq. De Laboratorio
H17: 06: Maquinarias
B20: Código Activo Fijo | C20: Moneda | D20: Importe Origen | E20: Importe Contable | F20: Valor Residual / Recupero Origen | G20: Valor Residual / Recupero Contable | H20: Rubro

Sheet Alta de Amortización Acumulada
A1: Alta de Amortizaciones Acumuladas Inicio | I1: Según Tabla | J1: Se debe ingresar en el sistema la parametrización previa, asi el sistema podrá leer las siglas correctamente
I3: Para ingresar a la Importación se debe dirigir a Utilidades >> Interfaces de Importación de Comprobantes >> Activo Fijo - Saldos Iniciales
J5: Dato Obligatorio
J6: Dato Automático
B7: Fecha de Hoy
B8: =+TODAY() -> 45594 | G8: 1 | H8: 2 | I8: 3 | J8: 4 | K8: 5 | L8: 6 | M8: 7 | N8: 8 | O8: 9 | P8: 10
G9: Fecha | H9: Texto (3) | J9: Texto (3) | M9: 0 | N9: 0 | O9: D
H10: Según Tabla | J10: Según Tabla
J11: CON: Contable
J12: IMP: Impositivo
J13: INF: Ajuste Por Inflacion
D14: Moneda Original | E14: Pesos
A15: Datos Accesorios para Cálculo Automático
A16: Fecha Activación | B16: Vida Util | C16: Código Activo Fijo | D16: Valor Origen | E16: Valor Contable | G16: Fecha Hasta Amortizado | H16: Clase de Comprobante | I16: Codigo de Activo Fijo | J16: Código Criterio | K16: Amortización Período Origen | L16: Amortización Período Contable | M16: Amort. Inicial Origen | N16: Amort. Inicial Contable | O16: Signo | P16: Años/Meses amortizados
C17: =+'Alta de Activo Fijo'!B21 -> 0 | D17: =+'Alta de Activo Fijo'!D21 -> 0 | E17: =+'Alta de Activo Fijo'!E21 -> 0 | I17: =+C17 -> 0 | J17: CON | K17: =+D17/B17*P17 -> #DIV/0! | L17: =+E17/B17*P17 -> #DIV/0! | M17: 0 | N17: 0 | O17: D | P17: =ROUND(IF(B17<(G17-A17)/30,+B17,(G17-A17)/30),0) -> 0
C18: =+'Alta de Activo Fijo'!B22 -> 0 | D18: =+'Alta de Activo Fijo'!D22 -> 0 | E18: =+'Alta de Activo Fijo'!E22 -> 0 | I18: =+C18 -> 0 | J18: CON | K18: =+D18/B18*P18 -> #DIV/0! | L18: =+E18/B18*P18 -> #DIV/0! | M18: 0 | N18: 0 | O18: D | P18: =ROUND(IF(B18<(G18-A18)/30,+B18,(G18-A18)/30),0) -> 0
C19: =+'Alta de Activo Fijo'!B23 -> 0 | D19: =+'Alta de Activo Fijo'!D23 -> 0 | E19: =+'Alta de Activo Fijo'!E23 -> 0 | I19: =+C19 -> 0 | J19: CON | K19: =+D19/B19*P19 -> #DIV/0! | L19: =+E19/B19*P19 -> #DIV/0! | M19: 0 | N19: 0 | O19: D | P19: =ROUND(IF(B19<(G19-A19)/30,+B19,(G19-A19)/30),0) -> 0
C20: =+'Alta de Activo Fijo'!B24 -> 0 | D20: =+'Alta de Activo Fijo'!D24 -> 0 | E20: =+'Alta de Activo Fijo'!E24 -> 0 | I20: =+C20 -> 0 | J20: CON | K20: =+D20/B20*P20 -> #DIV/0! | L20: =+E20/B20*P20 -> #DIV/0! | M20: 0 | N20: 0 | O20: D | P20: =ROUND(IF(B20<(G20-A20)/30,+B20,(G20-A20)/30),0) -> 0
C21: =+'Alta de Activo Fijo'!B25 -> 0 | D21: =+'Alta de Activo Fijo'!D25 -> 0 | E21: =+'Alta de Activo Fijo'!E25 -> 0 | I21: =+C21 -> 0 | J21: CON | K21: =+D21/B21*P21 -> #DIV/0! | L21: =+E21/B21*P21 -> #DIV/0! | M21: 0 | N21: 0 | O21: D | P21: =ROUND(IF(B21<(G21-A21)/30,+B21,(G21-A21)/30),0) -> 0
C22: =+'Alta de Activo Fijo'!B26 -> 0 | D22: =+'Alta de Activo Fijo'!D26 -> 0 | E22: =+'Alta de Activo Fijo'!E26 -> 0 | I22: =+C22 -> 0 | J22: CON | K22: =+D22/B22*P22 -> #DIV/0! | L22: =+E22/B22*P22 -> #DIV/0! | M22: 0 | N22: 0 | O22: D | P22: =ROUND(IF(B22<(G22-A22)/30,+B22,(G22-A22)/30),0) -> 0
C23: =+'Alta de Activo Fijo'!B27 -> 0 | D23: =+'Alta de Activo Fijo'!D27 -> 0 | E23: =+'Alta de Activo Fijo'!E27 -> 0 | I23: =+C23 -> 0 | J23: CON | K23: =+D23/B23*P23 -> #DIV/0! | L23: =+E23/B23*P23 -> #DIV/0! | M23: 0 | N23: 0 | O23: D | P23: =ROUND(IF(B23<(G23-A23)/30,+B23,(G23-A23)/30),0) -> 0
C24: =+'Alta de Activo Fijo'!B28 -> 0 | D24: =+'Alta de Activo Fijo'!D28 -> 0 | E24: =+'Alta de Activo Fijo'!E28 -> 0 | I24: =+C24 -> 0 | J24: CON | K24: =+D24/B24*P24 -> #DIV/0! | L24: =+E24/B24*P24 -> #DIV/0! | M24: 0 | N24: 0 | O24: D | P24: =ROUND(IF(B24<(G24-A24)/30,+B24,(G24-A24)/30),0) -> 0
C25: =+'Alta de Activo Fijo'!B29 -> 0 | D25: =+'Alta de Activo Fijo'!D29 -> 0 | E25: =+'Alta de Activo Fijo'!E29 -> 0 | I25: =+C25 -> 0 | J25: CON | K25: =+D25/B25*P25 -> #DIV/0! | L25: =+E25/B25*P25 -> #DIV/0! | M25: 0 | N25: 0 | O25: D | P25: =ROUND(IF(B25<(G25-A25)/30,+B25,(G25-A25)/30),0) -> 0
C26: =+'Alta de Activo Fijo'!B30 -> 0 | D26: =+'Alta de Activo Fijo'!D30 -> 0 | E26: =+'Alta de Activo Fijo'!E30 -> 0 | I26: =+C26 -> 0 | J26: CON | K26: =+D26/B26*P26 -> #DIV/0! | L26: =+E26/B26*P26 -> #DIV/0! | M26: 0 | N26: 0 | O26: D | P26: =ROUND(IF(B26<(G26-A26)/30,+B26,(G26-A26)/30),0) -> 0
C27: =+'Alta de Activo Fijo'!B31 -> 0 | D27: =+'Alta de Activo Fijo'!D31 -> 0 | E27: =+'Alta de Activo Fijo'!E31 -> 0 | I27: =+C27 -> 0 | J27: CON | K27: =+D27/B27*P27 -> #DIV/0! | L27: =+E27/B27*P27 -> #DIV/0! | M27: 0 | N27: 0 | O27: D | P27: =ROUND(IF(B27<(G27-A27)/30,+B27,(G27-A27)/30),0) -> 0
C28: =+'Alta de Activo Fijo'!B32 -> 0 | D28: =+'Alta de Activo Fijo'!D32 -> 0 | E28: =+'Alta de Activo Fijo'!E32 -> 0 | I28: =+C28 -> 0 | J28: CON | K28: =+D28/B28*P28 -> #DIV/0! | L28: =+E28/B28*P28 -> #DIV/0! | M28: 0 | N28: 0 | O28: D | P28: =ROUND(IF(B28<(G28-A28)/30,+B28,(G28-A28)/30),0) -> 0
... C198: =+'Alta de Activo Fijo'!B202 -> 0 | D198: =+'Alta de Activo Fijo'!D202 -> 0 | E198: =+'Alta de Activo Fijo'!E202 -> 0 | I198: =+C198 -> 0 | J198: CON | K198: =+D198/B198*P198 -> #DIV/0! | L198: =+E198/B198*P198 -> #DIV/0! | M198: 0 | N198: 0 | O198: D | P198: =ROUND(IF(B198<(G198-A198)/30,+B198,(G198-A198)/30),0) -> 0
