Workbook

Sheet Lista de Precios Venta 
A1: Maestro de Clientes Eventuales | F1: Se debe estar logueado con usuario SOPORTE subir la hoja "Subir a Global" desde Utilidades >> Incorporación de Datos de Planilla
B7: 1 | C7: 2 | D7: 3 | E7: 4 | F7: 5 | G7: 6 | H7: 7 | I7: 8 | J7: 9 | K7: 10
B8: texto(15) | C8: texto(70) | D8: según tabla | E8: texto(50) | F8: texto(15) | G8: texto(20) | H8: numero | I8: numero | J8: según tabla | K8: texto(100)
D9: RI= Responsable Inscripto | H9: 0 | I9: 0 | J9: 80=CUIT
D10: CF= Consumidor Final | H10: 1 | I10: 1 | J10: DNI=DNI
B13: CUIT / DNI | C13: Nombre | D13: Categoria de Iva | E13: Domicilio | F13: Codigo Postal | G13: Telefono | H13: tra | I13: Habilitado | J13: Tipo de Documento | K13: Mail
B14: 99999999 | C14: Tomás | D14: CF | E14: Comesaña 3949 | F14: 1714 | G14: 1199999999 | H14: 0 | I14: 1 | J14: 2 | K14: tomas@globaldynamics.com.ar

Sheet Subir a Global
A1: texto(15) | B1: texto(70) | C1: según tabla | D1: texto(50) | E1: texto(15) | F1: texto(20) | G1: numero | H1: numero | I1: según tabla | J1: texto(100)
A2: t7clieve | H2: 1 o 0
A3: c7clieve_cui | B3: c7clieve_nom | C3: c7clieve_idcativa | D3: c7clieve_dom | E3: c7clieve_codpos | F3: c7clieve_tel | G3: c7clieve_tra | H3: c7clieve_hab | I3: c7clieve_idtipdoc | J3: c7clieve_mai
A4: =+'Lista de Precios Venta '!B15 -> 0 | B4: =+'Lista de Precios Venta '!C15 -> 0 | C4: =+'Lista de Precios Venta '!D15 -> 0 | D4: =+'Lista de Precios Venta '!E15 -> 0 | E4: =+'Lista de Precios Venta '!F15 -> 0 | F4: =+'Lista de Precios Venta '!G15 -> 0 | G4: =+'Lista de Precios Venta '!H15 -> 0 | H4: =+'Lista de Precios Venta '!I15 -> 0 | ... J4: =+'Lista de Precios Venta '!K15 -> 0
A5: =+'Lista de Precios Venta '!B16 -> 0 | B5: =+'Lista de Precios Venta '!C16 -> 0 | C5: =+'Lista de Precios Venta '!D16 -> 0 | D5: =+'Lista de Precios Venta '!E16 -> 0 | E5: =+'Lista de Precios Venta '!F16 -> 0 | F5: =+'Lista de Precios Venta '!G16 -> 0 | G5: =+'Lista de Precios Venta '!H16 -> 0 | H5: =+'Lista de Precios Venta '!I16 -> 0 | ... J5: =+'Lista de Precios Venta '!K16 -> 0
A6: =+'Lista de Precios Venta '!B17 -> 0 | B6: =+'Lista de Precios Venta '!C17 -> 0 | C6: =+'Lista de Precios Venta '!D17 -> 0 | D6: =+'Lista de Precios Venta '!E17 -> 0 | E6: =+'Lista de Precios Venta '!F17 -> 0 | F6: =+'Lista de Precios Venta '!G17 -> 0 | G6: =+'Lista de Precios Venta '!H17 -> 0 | H6: =+'Lista de Precios Venta '!I17 -> 0 | ... J6: =+'Lista de Precios Venta '!K17 -> 0
A7: =+'Lista de Precios Venta '!B18 -> 0 | B7: =+'Lista de Precios Venta '!C18 -> 0 | C7: =+'Lista de Precios Venta '!D18 -> 0 | D7: =+'Lista de Precios Venta '!E18 -> 0 | E7: =+'Lista de Precios Venta '!F18 -> 0 | F7: =+'Lista de Precios Venta '!G18 -> 0 | G7: =+'Lista de Precios Venta '!H18 -> 0 | H7: =+'Lista de Precios Venta '!I18 -> 0 | ... J7: =+'Lista de Precios Venta '!K18 -> 0
A8: =+'Lista de Precios Venta '!B19 -> 0 | B8: =+'Lista de Precios Venta '!C19 -> 0 | C8: =+'Lista de Precios Venta '!D19 -> 0 | D8: =+'Lista de Precios Venta '!E19 -> 0 | E8: =+'Lista de Precios Venta '!F19 -> 0 | F8: =+'Lista de Precios Venta '!G19 -> 0 | G8: =+'Lista de Precios Venta '!H19 -> 0 | H8: =+'Lista de Precios Venta '!I19 -> 0 | ... J8: =+'Lista de Precios Venta '!K19 -> 0
A9: =+'Lista de Precios Venta '!B20 -> 0 | B9: =+'Lista de Precios Venta '!C20 -> 0 | C9: =+'Lista de Precios Venta '!D20 -> 0 | D9: =+'Lista de Precios Venta '!E20 -> 0 | E9: =+'Lista de Precios Venta '!F20 -> 0 | F9: =+'Lista de Precios Venta '!G20 -> 0 | G9: =+'Lista de Precios Venta '!H20 -> 0 | H9: =+'Lista de Precios Venta '!I20 -> 0 | ... J9: =+'Lista de Precios Venta '!K20 -> 0
A10: =+'Lista de Precios Venta '!B21 -> 0 | B10: =+'Lista de Precios Venta '!C21 -> 0 | C10: =+'Lista de Precios Venta '!D21 -> 0 | D10: =+'Lista de Precios Venta '!E21 -> 0 | E10: =+'Lista de Precios Venta '!F21 -> 0 | F10: =+'Lista de Precios Venta '!G21 -> 0 | G10: =+'Lista de Precios Venta '!H21 -> 0 | H10: =+'Lista de Precios Venta '!I21 -> 0 | ... J10: =+'Lista de Precios Venta '!K21 -> 0
A11: =+'Lista de Precios Venta '!B22 -> 0 | B11: =+'Lista de Precios Venta '!C22 -> 0 | C11: =+'Lista de Precios Venta '!D22 -> 0 | D11: =+'Lista de Precios Venta '!E22 -> 0 | E11: =+'Lista de Precios Venta '!F22 -> 0 | F11: =+'Lista de Precios Venta '!G22 -> 0 | G11: =+'Lista de Precios Venta '!H22 -> 0 | H11: =+'Lista de Precios Venta '!I22 -> 0 | ... J11: =+'Lista de Precios Venta '!K22 -> 0
A12: =+'Lista de Precios Venta '!B23 -> 0 | B12: =+'Lista de Precios Venta '!C23 -> 0 | C12: =+'Lista de Precios Venta '!D23 -> 0 | D12: =+'Lista de Precios Venta '!E23 -> 0 | E12: =+'Lista de Precios Venta '!F23 -> 0 | F12: =+'Lista de Precios Venta '!G23 -> 0 | G12: =+'Lista de Precios Venta '!H23 -> 0 | H12: =+'Lista de Precios Venta '!I23 -> 0 | ... J12: =+'Lista de Precios Venta '!K23 -> 0
A13: =+'Lista de Precios Venta '!B24 -> 0 | B13: =+'Lista de Precios Venta '!C24 -> 0 | C13: =+'Lista de Precios Venta '!D24 -> 0 | D13: =+'Lista de Precios Venta '!E24 -> 0 | E13: =+'Lista de Precios Venta '!F24 -> 0 | F13: =+'Lista de Precios Venta '!G24 -> 0 | G13: =+'Lista de Precios Venta '!H24 -> 0 | H13: =+'Lista de Precios Venta '!I24 -> 0 | ... J13: =+'Lista de Precios Venta '!K24 -> 0
A14: =+'Lista de Precios Venta '!B25 -> 0 | B14: =+'Lista de Precios Venta '!C25 -> 0 | C14: =+'Lista de Precios Venta '!D25 -> 0 | D14: =+'Lista de Precios Venta '!E25 -> 0 | E14: =+'Lista de Precios Venta '!F25 -> 0 | F14: =+'Lista de Precios Venta '!G25 -> 0 | G14: =+'Lista de Precios Venta '!H25 -> 0 | H14: =+'Lista de Precios Venta '!I25 -> 0 | ... J14: =+'Lista de Precios Venta '!K25 -> 0
A15: =+'Lista de Precios Venta '!B26 -> 0 | B15: =+'Lista de Precios Venta '!C26 -> 0 | C15: =+'Lista de Precios Venta '!D26 -> 0 | D15: =+'Lista de Precios Venta '!E26 -> 0 | E15: =+'Lista de Precios Venta '!F26 -> 0 | F15: =+'Lista de Precios Venta '!G26 -> 0 | G15: =+'Lista de Precios Venta '!H26 -> 0 | H15: =+'Lista de Precios Venta '!I26 -> 0 | ... J15: =+'Lista de Precios Venta '!K26 -> 0
... A1921: =+'Lista de Precios Venta '!B1932 -> 0 | B1921: =+'Lista de Precios Venta '!C1932 -> 0 | C1921: =+'Lista de Precios Venta '!D1932 -> 0 | D1921: =+'Lista de Precios Venta '!E1932 -> 0 | E1921: =+'Lista de Precios Venta '!F1932 -> 0 | F1921: =+'Lista de Precios Venta '!G1932 -> 0 | G1921: =+'Lista de Precios Venta '!H1932 -> 0 | H1921: =+'Lista de Precios Venta '!I1932 -> 0 | ... J1921: =+'Lista de Precios Venta '!K1932 -> 0
