Workbook

Sheet Plan de Cuentas
A1: Plan de Cuentas | F1: Nota: Esta importacion se debe realizar a través de Contabilidad >>> Plan de cuentas.
G2: Dato Obligatorio
G3: Dato Opcional
G4: Vacio
D6: 0 | E6: 1 | F6: 2 | G6: 3 | H6: 4 | I6: 5 | J6: 6 | K6: 7 | L6: 8 | M6: 9 | N6: 10 | O6: 11 | P6: 12 | Q6: 13 | R6: 14 | S6: 15 | T6: 16 | U6: 17 | V6: 18 | W6: 19 | X6: 20 | Y6: 21 | Z6: 22 | AA6: 23 | AB6: 24 | AC6: 25 | AD6: 26 | AE6: 27 | AF6: 28 | AG6: 29 | AH6: 30 | AI6: 31 | AJ6: 32 | AK6: 33 | AL6: 34 | AM6: 35
G7: 1 - 0 | H7: 1 - 0 | I7: D - H | J7: 1 - 0 | K7: 1 - 0 | L7: 1 - 0 | N7: 1 - 0 | O7: 1 - 0 | P7: 1 - 0 | Q7: 1 - 0 | R7: 1 - 0 | U7: Cuenta Contable | X7: 1 - 0 | Y7: 1 - 0 | Z7: 1 - 0 | AA7: 1 - 0 | AB7: 1 - 0 | AC7: 1 - 0 | AD7: 1 - 0 | AE7: 1 - 0 | AF7: 1 - 0 | AG7: 1 - 0
O10: Tipo de Apertura por Auxiliar | X10: Control de Imputabilidad | AI10: Habilitacion por Unidad de Negocios
D11: Cod de Cuenta | E11: Nombre | F11: Moneda | G11: Imputable | H11: Habilitada | I11: Saldo Habitual | J11: Resultado | K11: Monetaria | L11: Imputable por Parametros | M11: Auxiliar | N11: Hab. Elem por Auxiliar | O11: Cliente | P11: Proveedor | Q11: Empleado | R11: Alternativo | S11: Esq. De Distribucion | T11: Auxiliar Alternativo | U11: Cta Alternativa Ajuste x Inflacion | X11: Contabilidad | Y11: Ctas a Pagar Pagos | Z11: Ctas a Cobrar Recibos | AA11: Bancos | AB11: Ctas a Pagar Fact | AC11: Ctas a Cobrar Fact | AD11: Inventario | AE11: Activo Fijo | AF11: Punto de Vta | AG11: RRHH | AI11: Un de Negocios | AJ11: Un de Negocios | AK11: Un de Negocios | AL11: Un de Negocios | AM11: Un de Negocios
C12: Ejemplo | D12: 1.30.101 | E12: Activo Nuevo | F12: ARS | G12: 1 | H12: 1 | I12: D | J12: 1 | K12: 0 | L12: 0 | M12: CC | N12: 0 | O12: 0 | P12: 0 | Q12: 0 | R12: 0 | X12: 1 | Y12: 1 | Z12: 1 | AA12: 1 | AB12: 0 | AC12: 1 | AD12: 1 | AE12: 0 | AF12: 1 | AG12: 1 | AI12: 1
D13: =+Hoja1!A4 -> 1. | E13: =+Hoja1!B4 -> ACTIVO | F13: =+Hoja1!E4 -> PS | G13: =IF(Hoja1!F4="NO",0,1) -> 0 | H13: =IF(Hoja1!I4="NO",0,1) -> 1 | I13: D | J13: =IF(Hoja1!G4="NO",0,1) -> 0 | K13: =IF(Hoja1!H4="NO",0,1) -> 1 | L13: 0 | N13: 0 | O13: 0 | P13: 0 | Q13: 0 | R13: 0 | X13: =IF(G13=1,1,0) -> 0 | Y13: 0 | Z13: 0 | AA13: 0 | AB13: 0 | AC13: 0 | AD13: 0 | AE13: 0 | AF13: 0 | AG13: 0
D14: =+Hoja1!A5 -> 1.1. | E14: =+Hoja1!B5 -> ACTIVO CORRIENTE | F14: =+Hoja1!E5 -> PS | G14: =IF(Hoja1!F5="NO",0,1) -> 0 | H14: =IF(Hoja1!I5="NO",0,1) -> 1 | I14: D | J14: =IF(Hoja1!G5="NO",0,1) -> 0 | K14: =IF(Hoja1!H5="NO",0,1) -> 1 | L14: 0 | N14: 0 | O14: 0 | P14: 0 | Q14: 0 | R14: 0 | X14: =IF(G14=1,1,0) -> 0 | Y14: 0 | Z14: 0 | AA14: 0 | AB14: 0 | AC14: 0 | AD14: 0 | AE14: 0 | AF14: 0 | AG14: 0
D15: =+Hoja1!A6 -> 1101 | E15: =+Hoja1!B6 -> DISPONIBILIDADES | F15: =+Hoja1!E6 -> PS | G15: =IF(Hoja1!F6="NO",0,1) -> 0 | H15: =IF(Hoja1!I6="NO",0,1) -> 1 | I15: D | J15: =IF(Hoja1!G6="NO",0,1) -> 0 | K15: =IF(Hoja1!H6="NO",0,1) -> 1 | L15: 0 | N15: 0 | O15: 0 | P15: 0 | Q15: 0 | R15: 0 | X15: =IF(G15=1,1,0) -> 0 | Y15: 0 | Z15: 0 | AA15: 0 | AB15: 0 | AC15: 0 | AD15: 0 | AE15: 0 | AF15: 0 | AG15: 0
D16: =+Hoja1!A7 -> 110101 | E16: =+Hoja1!B7 -> CAJA | F16: =+Hoja1!E7 -> PS | G16: =IF(Hoja1!F7="NO",0,1) -> 1 | H16: =IF(Hoja1!I7="NO",0,1) -> 1 | I16: D | J16: =IF(Hoja1!G7="NO",0,1) -> 0 | K16: =IF(Hoja1!H7="NO",0,1) -> 1 | L16: 0 | N16: 0 | O16: 0 | P16: 0 | Q16: 0 | R16: 0 | X16: =IF(G16=1,1,0) -> 1 | Y16: 0 | Z16: 0 | AA16: 0 | AB16: 0 | AC16: 0 | AD16: 0 | AE16: 0 | AF16: 0 | AG16: 0
D17: =+Hoja1!A8 -> 110101001 | E17: =+Hoja1!B8 -> EFECTIVO - MONEDA NACIONAL | F17: =+Hoja1!E8 -> PS | G17: =IF(Hoja1!F8="NO",0,1) -> 1 | H17: =IF(Hoja1!I8="NO",0,1) -> 1 | I17: D | J17: =IF(Hoja1!G8="NO",0,1) -> 0 | K17: =IF(Hoja1!H8="NO",0,1) -> 1 | L17: 0 | N17: 0 | O17: 0 | P17: 0 | Q17: 0 | R17: 0 | X17: =IF(G17=1,1,0) -> 1 | Y17: 0 | Z17: 0 | AA17: 0 | AB17: 0 | AC17: 0 | AD17: 0 | AE17: 0 | AF17: 0 | AG17: 0
D18: =+Hoja1!A9 -> 110101002 | E18: =+Hoja1!B9 -> EFECTIVO - MONEDA EXTRANJERA | F18: =+Hoja1!E9 -> PS | G18: =IF(Hoja1!F9="NO",0,1) -> 1 | H18: =IF(Hoja1!I9="NO",0,1) -> 1 | I18: D | J18: =IF(Hoja1!G9="NO",0,1) -> 0 | K18: =IF(Hoja1!H9="NO",0,1) -> 1 | L18: 0 | N18: 0 | O18: 0 | P18: 0 | Q18: 0 | R18: 0 | X18: =IF(G18=1,1,0) -> 1 | Y18: 0 | Z18: 0 | AA18: 0 | AB18: 0 | AC18: 0 | AD18: 0 | AE18: 0 | AF18: 0 | AG18: 0
D19: =+Hoja1!A10 -> 110101010 | E19: =+Hoja1!B10 -> CAJA CHICA | F19: =+Hoja1!E10 -> PS | G19: =IF(Hoja1!F10="NO",0,1) -> 1 | H19: =IF(Hoja1!I10="NO",0,1) -> 1 | I19: D | J19: =IF(Hoja1!G10="NO",0,1) -> 0 | K19: =IF(Hoja1!H10="NO",0,1) -> 1 | L19: 0 | N19: 0 | O19: 0 | P19: 0 | Q19: 0 | R19: 0 | X19: =IF(G19=1,1,0) -> 1 | Y19: 0 | Z19: 0 | AA19: 0 | AB19: 0 | AC19: 0 | AD19: 0 | AE19: 0 | AF19: 0 | AG19: 0
D20: =+Hoja1!A11 -> 110105 | E20: =+Hoja1!B11 -> BANCOS | F20: =+Hoja1!E11 -> PS | G20: =IF(Hoja1!F11="NO",0,1) -> 0 | H20: =IF(Hoja1!I11="NO",0,1) -> 1 | I20: D | J20: =IF(Hoja1!G11="NO",0,1) -> 0 | K20: =IF(Hoja1!H11="NO",0,1) -> 1 | L20: 0 | N20: 0 | O20: 0 | P20: 0 | Q20: 0 | R20: 0 | X20: =IF(G20=1,1,0) -> 0 | Y20: 0 | Z20: 0 | AA20: 0 | AB20: 0 | AC20: 0 | AD20: 0 | AE20: 0 | AF20: 0 | AG20: 0
D21: =+Hoja1!A12 -> 110105110 | E21: =+Hoja1!B12 -> BANCO ARS | F21: =+Hoja1!E12 -> PS | G21: =IF(Hoja1!F12="NO",0,1) -> 1 | H21: =IF(Hoja1!I12="NO",0,1) -> 1 | I21: D | J21: =IF(Hoja1!G12="NO",0,1) -> 0 | K21: =IF(Hoja1!H12="NO",0,1) -> 1 | L21: 0 | N21: 0 | O21: 0 | P21: 0 | Q21: 0 | R21: 0 | X21: =IF(G21=1,1,0) -> 1 | Y21: 0 | Z21: 0 | AA21: 0 | AB21: 0 | AC21: 0 | AD21: 0 | AE21: 0 | AF21: 0 | AG21: 0
D22: =+Hoja1!A13 -> 110105111 | E22: =+Hoja1!B13 -> BANCO USD | F22: =+Hoja1!E13 -> DL | G22: =IF(Hoja1!F13="NO",0,1) -> 1 | H22: =IF(Hoja1!I13="NO",0,1) -> 1 | I22: D | J22: =IF(Hoja1!G13="NO",0,1) -> 0 | K22: =IF(Hoja1!H13="NO",0,1) -> 1 | L22: 0 | N22: 0 | O22: 0 | P22: 0 | Q22: 0 | R22: 0 | X22: =IF(G22=1,1,0) -> 1 | Y22: 0 | Z22: 0 | AA22: 0 | AB22: 0 | AC22: 0 | AD22: 0 | AE22: 0 | AF22: 0 | AG22: 0
D23: =+Hoja1!A14 -> 110105121 | E23: =+Hoja1!B14 -> REGULARIZADORA DE BANCOS | F23: =+Hoja1!E14 -> PS | G23: =IF(Hoja1!F14="NO",0,1) -> 1 | H23: =IF(Hoja1!I14="NO",0,1) -> 1 | I23: D | J23: =IF(Hoja1!G14="NO",0,1) -> 0 | K23: =IF(Hoja1!H14="NO",0,1) -> 1 | L23: 0 | N23: 0 | O23: 0 | P23: 0 | Q23: 0 | R23: 0 | X23: =IF(G23=1,1,0) -> 1 | Y23: 0 | Z23: 0 | AA23: 0 | AB23: 0 | AC23: 0 | AD23: 0 | AE23: 0 | AF23: 0 | AG23: 0
D24: =+Hoja1!A15 -> 110105148 | E24: =+Hoja1!B15 -> MERCADO PAGO | F24: =+Hoja1!E15 -> PS | G24: =IF(Hoja1!F15="NO",0,1) -> 1 | H24: =IF(Hoja1!I15="NO",0,1) -> 1 | I24: D | J24: =IF(Hoja1!G15="NO",0,1) -> 0 | K24: =IF(Hoja1!H15="NO",0,1) -> 1 | L24: 0 | N24: 0 | O24: 0 | P24: 0 | Q24: 0 | R24: 0 | X24: =IF(G24=1,1,0) -> 1 | Y24: 0 | Z24: 0 | AA24: 0 | AB24: 0 | AC24: 0 | AD24: 0 | AE24: 0 | AF24: 0 | AG24: 0
... D490: =+Hoja1!A481 -> 5501 | E490: =+Hoja1!B481 -> OTROS EGRESOS EXTRAORDINARIOS | F490: =+Hoja1!E481 -> PS | G490: =IF(Hoja1!F481="NO",0,1) -> 1 | H490: =IF(Hoja1!I481="NO",0,1) -> 1 | I490: D | J490: =IF(Hoja1!G481="NO",0,1) -> 1 | K490: =IF(Hoja1!H481="NO",0,1) -> 0 | L490: 0 | N490: 0 | O490: 0 | P490: 0 | Q490: 0 | R490: 0 | X490: =IF(G490=1,1,0) -> 1 | Y490: 0 | Z490: 0 | AA490: 0 | AB490: 0 | AC490: 0 | AD490: 0 | AE490: 0 | AF490: 0 | AG490: 0

Sheet Hoja1
A1: Empresa Modelo
A2: Plan de Cuentas
A3: Código | B3: Nombre | C3: Type 1 | D3: Type 2 | E3: Moneda | F3: Imp. | G3: Res. | H3: Mon. | I3: Hab. | L3: 1 | Q3: =CONCATENATE(L3,".") -> 1.
A4: 1. | B4: ACTIVO | C4: activ | D4: BS | E4: PS | F4: No | G4: No | H4: Si | I4: Si | L4: 1 | M4: 1
A5: 1.1. | B5: ACTIVO CORRIENTE | C5: activ | D5: BS | E5: PS | F5: No | G5: No | H5: Si | I5: Si | L5: 1 | M5: 1 | N5: 1
A6: 1101 | B6: DISPONIBILIDADES | C6: activ | D6: BS | E6: PS | F6: No | G6: No | H6: Si | I6: Si | L6: 1 | M6: 1 | N6: 1 | O6: 1
A7: 110101 | B7: CAJA | C7: activ | D7: BS | E7: PS | F7: Si | G7: No | H7: Si | I7: Si | L7: 1 | M7: 1 | N7: 1 | O7: 1 | P7: 1
A8: 110101001 | B8: EFECTIVO - MONEDA NACIONAL | C8: activ | D8: BS | E8: PS | F8: Si | G8: No | H8: Si | I8: Si | L8: 1 | M8: 1 | N8: 1 | O8: 1 | P8: 2
A9: 110101002 | B9: EFECTIVO - MONEDA EXTRANJERA | C9: activ | D9: BS | E9: PS | F9: Si | G9: No | H9: Si | I9: Si | L9: 1 | M9: 1 | N9: 1 | O9: 1 | P9: 10
A10: 110101010 | B10: CAJA CHICA | C10: activ | D10: BS | E10: PS | F10: Si | G10: No | H10: Si | I10: Si | L10: 1 | M10: 1 | N10: 1 | O10: 5
A11: 110105 | B11: BANCOS | C11: activ | D11: BS | E11: PS | F11: No | G11: No | H11: Si | I11: Si | L11: 1 | M11: 1 | N11: 1 | O11: 5 | P11: 110
A12: 110105110 | B12: BANCO ARS | C12: activ | D12: BS | E12: PS | F12: Si | G12: No | H12: Si | I12: Si | L12: 1 | M12: 1 | N12: 1 | O12: 5 | P12: 111
A13: 110105111 | B13: BANCO USD | C13: activ | D13: BS | E13: DL | F13: Si | G13: No | H13: Si | I13: Si | L13: 1 | M13: 1 | N13: 1 | O13: 5 | P13: 121
A14: 110105121 | B14: REGULARIZADORA DE BANCOS | C14: activ | D14: BS | E14: PS | F14: Si | G14: No | H14: Si | I14: Si | L14: 1 | M14: 1 | N14: 1 | O14: 5 | P14: 148
A15: 110105148 | B15: MERCADO PAGO | C15: activ | D15: BS | E15: PS | F15: Si | G15: No | H15: Si | I15: Si | L15: 1 | M15: 1 | N15: 2
A16: 1102 | B16: INVERSIONES | C16: activ | D16: BS | E16: PS | F16: No | G16: No | H16: Si | I16: Si | L16: 1 | M16: 1 | N16: 2 | O16: 1
A17: 110201 | B17: PLAZOS FIJOS | C17: activ | D17: BS | E17: PS | F17: No | G17: No | H17: Si | I17: Si | L17: 1 | M17: 1 | N17: 2 | O17: 1 | P17: 10
A18: 110201010 | B18: INVERSIONES | C18: activ | D18: BS | E18: PS | F18: Si | G18: No | H18: Si | I18: Si | L18: 1 | M18: 1 | N18: 2 | O18: 2
A19: 110202 | B19: BONOS | C19: activ | D19: BS | E19: PS | F19: No | G19: No | H19: Si | I19: Si | L19: 1 | M19: 1 | N19: 2 | O19: 2 | P19: 1
A20: 110202001 | B20: CUENTA COMITENTE | C20: activ | D20: BS | E20: PS | F20: Si | G20: No | H20: Si | I20: Si | L20: 1 | M20: 1 | N20: 2 | O20: 2 | P20: 9
A21: 110202009 | B21: ACCIONES | C21: activ | D21: BS | E21: PS | F21: Si | G21: No | H21: Si | I21: Si | L21: 1 | M21: 1 | N21: 2 | O21: 3 | P21: 10
A22: 110203010 | B22: TÍTULOS PUBLICOS USD | C22: activ | D22: BS | E22: DL | F22: Si | G22: No | H22: Si | I22: Si | L22: 1 | M22: 1 | N22: 2 | O22: 3 | P22: 12
A23: 110203012 | B23: FONDO COMÚN DE INVERSIONES ARS | C23: activ | D23: BS | E23: DL | F23: Si | G23: No | H23: Si | I23: Si | L23: 1 | M23: 1 | N23: 2 | O23: 3 | P23: 14
A24: 110203014 | B24: FONDO COMÚN DE INVERSIONES USD | C24: activ | D24: BS | E24: PS | F24: Si | G24: No | H24: Si | I24: Si | L24: 1 | M24: 1 | N24: 3
A25: 1103 | B25: CREDITOS POR VENTAS | C25: activ | D25: BS | E25: PS | F25: No | G25: No | H25: Si | I25: Si | L25: 1 | M25: 1 | N25: 3 | O25: 1
A26: 110301 | B26: CREDITOS POR VENTAS | C26: activ | D26: BS | E26: PS | F26: No | G26: No | H26: Si | I26: Si | L26: 1 | M26: 1 | N26: 3 | O26: 1 | P26: 1
A27: 110301001 | B27: DEUDORES POR VENTAS | C27: activ | D27: BS | E27: PS | F27: Si | G27: No | H27: Si | I27: Si | L27: 1 | M27: 1 | N27: 3 | O27: 1 | P27: 2
A28: 110301002 | B28: DEUDORES DEL EXTERIOR | C28: activ | D28: BS | E28: PS | F28: Si | G28: No | H28: Si | I28: Si | L28: 1 | M28: 1 | N28: 3 | O28: 1 | P28: 10
A29: 110301010 | B29: RECAUDADORA DE CLIENTE | C29: activ | D29: BS | E29: PS | F29: Si | G29: No | H29: Si | I29: Si | L29: 1 | M29: 1 | N29: 3 | O29: 1 | P29: 20
A30: 110301020 | B30: COBRANZAS PEND. MERC.EXT | C30: activ | D30: BS | E30: DL | F30: Si | G30: No | H30: Si | I30: Si | L30: 1 | M30: 1 | N30: 3 | O30: 1 | P30: 25
A31: 110301025 | B31: DOCUMENTOS A COBRAR | C31: activ | D31: BS | E31: PS | F31: Si | G31: No | H31: Si | I31: Si | L31: 1 | M31: 1 | N31: 3 | O31: 1 | P31: 30
A32: 110301030 | B32: DOCUMENTOS EN GESTION | C32: activ | D32: BS | E32: PS | F32: Si | G32: No | H32: Si | I32: Si | L32: 1 | M32: 1 | N32: 3 | O32: 1 | P32: 70
A33: 110301070 | B33: PREVISION PARA DS. INCOBR. | C33: activ | D33: BS | E33: PS | F33: Si | G33: No | H33: Si | I33: Si | L33: 1 | M33: 1 | N33: 3 | O33: 5
A34: 110305 | B34: VALORES A DEPOSITAR | C34: activ | D34: BS | E34: PS | F34: No | G34: No | H34: Si | I34: Si | L34: 1 | M34: 1 | N34: 3 | O34: 5 | P34: 1
A35: 110305001 | B35: VALORES PROPIOS DE CLIENTES | C35: activ | D35: BS | E35: PS | F35: Si | G35: No | H35: Si | I35: Si | L35: 1 | M35: 1 | N35: 3 | O35: 5 | P35: 10
A36: 110305010 | B36: VALORES DE TERCEROS | C36: activ | D36: BS | E36: PS | F36: Si | G36: No | H36: Si | I36: Si | L36: 1 | M36: 1 | N36: 3 | O36: 5 | P36: 20
A37: 110305020 | B37: VALORES ENTREGADOS EN CUSTODIA | C37: activ | D37: BS | E37: PS | F37: Si | G37: No | H37: Si | I37: Si | L37: 1 | M37: 1 | N37: 3 | O37: 5 | P37: 30
A38: 110305030 | B38: VALORES RECHAZADOS | C38: activ | D38: BS | E38: PS | F38: Si | G38: No | H38: Si | I38: Si | L38: 1 | M38: 1 | N38: 3 | O38: 5 | P38: 40
A39: 110305040 | B39: VALORES DE 3EROS. P/ GESTIONAR | C39: activ | D39: BS | E39: PS | F39: Si | G39: No | H39: Si | I39: Si | L39: 1 | M39: 1 | N39: 4
A40: 1104 | B40: OTROS CREDITOS | C40: activ | D40: BS | E40: PS | F40: No | G40: No | H40: Si | I40: Si | L40: 1 | M40: 1 | N40: 4 | O40: 1
A41: 110401 | B41: OTROS CREDITOS | C41: activ | D41: BS | E41: PS | F41: No | G41: No | H41: Si | I41: Si | L41: 1 | M41: 1 | N41: 4 | O41: 1 | P41: 1
A42: 110401001 | B42: ACCIONISTAS | C42: activ | D42: BS | E42: PS | F42: Si | G42: No | H42: Si | I42: Si | L42: 1 | M42: 1 | N42: 4 | O42: 1 | P42: 2
A43: 110401002 | B43: GASTOS A RECUPERAR ARS | C43: activ | D43: BS | E43: PS | F43: Si | G43: No | H43: Si | I43: Si | L43: 1 | M43: 1 | N43: 4 | O43: 1 | P43: 4
A44: 110401004 | B44: ACCIONISTAS (AUX) | C44: activ | D44: BS | E44: PS | F44: Si | G44: No | H44: Si | I44: Si | L44: 1 | M44: 1 | N44: 4 | O44: 1 | P44: 5
A45: 110401005 | B45: ANTICIPOS A PROVEEDORES | C45: activ | D45: BS | E45: PS | F45: Si | G45: No | H45: Si | I45: Si | L45: 1 | M45: 1 | N45: 4 | O45: 1 | P45: 10
A46: 110401010 | B46: DEPOSITOS EN GARANTIA | C46: activ | D46: BS | E46: PS | F46: Si | G46: No | H46: Si | I46: Si | L46: 1 | M46: 1 | N46: 4 | O46: 1 | P46: 20
A47: 110401020 | B47: REEM. POR EXP. A COBRAR | C47: activ | D47: BS | E47: PS | F47: Si | G47: No | H47: Si | I47: Si | L47: 1 | M47: 1 | N47: 4 | O47: 1 | P47: 30
A48: 110401030 | B48: CUENTAS DIRECTORES | C48: activ | D48: BS | E48: PS | F48: Si | G48: No | H48: Si | I48: Si | L48: 1 | M48: 1 | N48: 4 | O48: 1 | P48: 40
A49: 110401040 | B49: INTERESES A DEVENGAR | C49: activ | D49: BS | E49: PS | F49: Si | G49: No | H49: Si | I49: Si | L49: 1 | M49: 1 | N49: 4 | O49: 1 | P49: 50
A50: 110401050 | B50: SEGUROS A DEVENGAR | C50: activ | D50: BS | E50: PS | F50: Si | G50: No | H50: Si | I50: Si | L50: 1 | M50: 1 | N50: 4 | O50: 1 | P50: 55
A51: 110401055 | B51: GASTOS A DEVENGAR | C51: activ | D51: BS | E51: PS | F51: Si | G51: No | H51: Si | I51: Si | L51: 1 | M51: 1 | N51: 4 | O51: 1 | P51: 70
A52: 110401070 | B52: GS.PAGADOS P/ADELANTADO | C52: activ | D52: BS | E52: PS | F52: Si | G52: No | H52: Si | I52: Si | L52: 1 | M52: 1 | N52: 4 | O52: 1 | P52: 81
... A60: 110401130 | B60: OTROS CRÉDITOS | C60: activ | D60: BS | E60: PS | F60: Si | G60: No | H60: Si | I60: Si | L60: 1 | M60: 1 | N60: 4 | O60: 1 | P60: 131
A61: 110401131 | B61: CREDITO FINANCIERO | C61: activ | D61: BS | E61: PS | F61: Si | G61: No | H61: Si | I61: Si | L61: 1 | M61: 1 | N61: 4 | O61: 5
A62: 110405 | B62: CREDITOS IMPOSITIVOS IG | C62: activ | D62: BS | E62: PS | F62: No | G62: No | H62: Si | I62: Si | L62: 1 | M62: 1 | N62: 4 | O62: 5 | P62: 1
A63: 110405001 | B63: RETENCIONES GANANCIAS CLIENTES | C63: activ | D63: BS | E63: PS | F63: Si | G63: No | H63: Si | I63: Si | L63: 1 | M63: 1 | N63: 4 | O63: 5 | P63: 10
A64: 110405010 | B64: RETENCIONES IVA CLIENTES | C64: activ | D64: BS | E64: PS | F64: Si | G64: No | H64: Si | I64: Si | L64: 1 | M64: 1 | N64: 4 | O64: 5 | P64: 15
A65: 110405015 | B65: RETENCION SUSS CLIENTES | C65: activ | D65: BS | E65: PS | F65: Si | G65: No | H65: Si | I65: Si | L65: 1 | M65: 1 | N65: 4 | O65: 5 | P65: 17
A66: 110405017 | B66: RETENCION IIBB CAPITAL CLIENTE | C66: activ | D66: BS | E66: PS | F66: Si | G66: No | H66: Si | I66: Si | L66: 1 | M66: 1 | N66: 4 | O66: 5 | P66: 20
A67: 110405020 | B67: PERCEPCIÓN LEY 25413 | C67: activ | D67: BS | E67: PS | F67: Si | G67: No | H67: Si | I67: Si | L67: 1 | M67: 1 | N67: 4 | O67: 5 | P67: 25
A68: 110405025 | B68: IMPUESTO AL CHEQUE LEY 25413 | C68: activ | D68: BS | E68: PS | F68: Si | G68: No | H68: Si | I68: Si | L68: 1 | M68: 1 | N68: 4 | O68: 5 | P68: 30
A69: 110405030 | B69: IMPUESTOS A LAS GCIAS 3% | C69: activ | D69: BS | E69: PS | F69: Si | G69: No | H69: Si | I69: Si | L69: 1 | M69: 1 | N69: 4 | O69: 5 | P69: 40
A70: 110405040 | B70: PERCEP GCIA RG 3378 15% C.EXT | C70: activ | D70: BS | E70: PS | F70: Si | G70: No | H70: Si | I70: Si | L70: 1 | M70: 1 | N70: 4 | O70: 5 | P70: 45
A71: 110405045 | B71: PERCEP GCIA RG 4815 35% EXTERIOR | C71: activ | D71: BS | E71: PS | F71: Si | G71: No | H71: Si | I71: Si | L71: 1 | M71: 1 | N71: 4 | O71: 5 | P71: 50
A72: 110405050 | B72: SALDO GCIAS DDJJ LIBRE DISPON. | C72: activ | D72: BS | E72: PS | F72: Si | G72: No | H72: Si | I72: Si | L72: 1 | M72: 1 | N72: 4 | O72: 5 | P72: 51
A73: 110405051 | B73: SALDO A FAVOR DDJJ GCIAS | C73: activ | D73: BS | E73: PS | F73: Si | G73: No | H73: Si | I73: Si | L73: 1 | M73: 1 | N73: 4 | O73: 5 | P73: 70
A74: 110405070 | B74: ANTICIPOS GANANCIAS | C74: activ | D74: BS | E74: PS | F74: Si | G74: No | H74: Si | I74: Si | L74: 1 | M74: 1 | N74: 4 | O74: 5 | P74: 80
A75: 110405080 | B75: ACTIVO POR IMP. DIFERIDO | C75: activ | D75: BS | E75: PS | F75: Si | G75: No | H75: Si | I75: Si | L75: 1 | M75: 1 | N75: 4 | O75: 15
A76: 110415 | B76: CREDITOS IMPOSITIVOS-IVA | C76: activ | D76: BS | E76: PS | F76: No | G76: No | H76: Si | I76: Si | L76: 1 | M76: 1 | N76: 4 | O76: 15 | P76: 1
A77: 110415001 | B77: IVA CRED.FISCAL | C77: activ | D77: BS | E77: PS | F77: Si | G77: No | H77: Si | I77: Si | L77: 1 | M77: 1 | N77: 4 | O77: 15 | P77: 30
A78: 110415030 | B78: IVA PERCEP. RG.Nº 3337 | C78: activ | D78: BS | E78: PS | F78: Si | G78: No | H78: Si | I78: Si | L78: 1 | M78: 1 | N78: 4 | O78: 15 | P78: 31
A79: 110415031 | B79: IVA RETENCIONES | C79: activ | D79: BS | E79: PS | F79: No | G79: No | H79: No | I79: Si | L79: 1 | M79: 1 | N79: 4 | O79: 15 | P79: 40
A80: 110415040 | B80: RET. IVA R.G. Nº 3625 | C80: activ | D80: BS | E80: PS | F80: Si | G80: No | H80: Si | I80: Si | L80: 1 | M80: 1 | N80: 4 | O80: 15 | P80: 50
A81: 110415050 | B81: IVA PERCEPC. ADUANA | C81: activ | D81: BS | E81: PS | F81: Si | G81: No | H81: Si | I81: Si | L81: 1 | M81: 1 | N81: 4 | O81: 15 | P81: 60
A82: 110415060 | B82: IVA SALDO A FAVOR TECNICO | C82: activ | D82: BS | E82: PS | F82: Si | G82: No | H82: Si | I82: Si | L82: 1 | M82: 1 | N82: 4 | O82: 15 | P82: 70
A83: 110415070 | B83: IVA SALDO LIBRE DISPONIBILIDAD | C83: activ | D83: BS | E83: PS | F83: Si | G83: No | H83: Si | I83: Si | L83: 1 | M83: 1 | N83: 4 | O83: 15 | P83: 76
A84: 110415076 | B84: IVA CRED FISCAL A COMPUTAR | C84: activ | D84: BS | E84: PS | F84: Si | G84: No | H84: Si | I84: Si | L84: 1 | M84: 1 | N84: 4 | O84: 15 | P84: 80
A85: 110415080 | B85: SOLICITUD REINTEGRO EXPORT. | C85: activ | D85: BS | E85: PS | F85: Si | G85: No | H85: Si | I85: Si | L85: 1 | M85: 1 | N85: 4 | O85: 18
A86: 110418 | B86: CREDITOS IMPOSITIVOS IIBB | C86: activ | D86: BS | E86: PS | F86: No | G86: No | H86: Si | I86: Si | L86: 1 | M86: 1 | N86: 4 | O86: 18 | P86: 16
A87: 110418016 | B87: IIBB RETENCION BS AS | C87: activ | D87: BS | E87: PS | F87: Si | G87: No | H87: Si | I87: Si | L87: 1 | M87: 1 | N87: 4 | O87: 18 | P87: 17
A88: 110418017 | B88: IIBB PERCEPCIÓN BS AS | C88: activ | D88: BS | E88: PS | F88: Si | G88: No | H88: Si | I88: Si | L88: 1 | M88: 1 | N88: 4 | O88: 18 | P88: 20
A89: 110418020 | B89: OTROS CREDITOS IIBB | C89: activ | D89: BS | E89: PS | F89: Si | G89: No | H89: Si | I89: Si | L89: 1 | M89: 1 | N89: 4 | O89: 18 | P89: 25
A90: 110418025 | B90: SALDO A FAVOR IIBB CAP. | C90: activ | D90: BS | E90: PS | F90: Si | G90: No | H90: Si | I90: Si | L90: 1 | M90: 1 | N90: 4 | O90: 18 | P90: 26
A91: 110418026 | B91: SALDO A FAVOR IIBB BS.AS. | C91: activ | D91: BS | E91: PS | F91: Si | G91: No | H91: Si | I91: Si | L91: 1 | M91: 1 | N91: 4 | O91: 20
A92: 110420 | B92: CREDITOS IMPOSITIVOS - OTROS | C92: activ | D92: BS | E92: PS | F92: No | G92: No | H92: Si | I92: Si | L92: 1 | M92: 1 | N92: 4 | O92: 20 | P92: 2
A93: 110420002 | B93: CREDITO IMP.LEY 25413 | C93: activ | D93: BS | E93: PS | F93: Si | G93: No | H93: Si | I93: Si | L93: 1 | M93: 1 | N93: 4 | O93: 20 | P93: 10
A94: 110420010 | B94: OTROS CREDITOS IMPOSITIVOS | C94: activ | D94: BS | E94: PS | F94: Si | G94: No | H94: Si | I94: Si | L94: 1 | M94: 1 | N94: 4 | O94: 20 | P94: 50
A95: 110420050 | B95: PERC. ING BRUTOS-SIRCREB CAPITAL | C95: activ | D95: BS | E95: PS | F95: Si | G95: No | H95: Si | I95: Si | L95: 1 | M95: 1 | N95: 4 | O95: 20 | P95: 55
A96: 110420055 | B96: PERC. ING BRUTOS-SIRCREB BS AS | C96: activ | D96: BS | E96: PS | F96: Si | G96: No | H96: Si | I96: Si | L96: 1 | M96: 1 | N96: 5
A97: 1105 | B97: BIENES DE CAMBIO | C97: activ | D97: BS | E97: PS | F97: No | G97: No | H97: Si | I97: Si | L97: 1 | M97: 1 | N97: 5 | O97: 1
A98: 110501 | B98: MATERIAS PRIMAS NACIONALES | C98: activ | D98: BS | E98: PS | F98: No | G98: No | H98: Si | I98: Si | L98: 1 | M98: 1 | N98: 5 | O98: 5
A99: 110505 | B99: MATERIA PRIMAS IMPORTADAS | C99: activ | D99: BS | E99: DL | F99: No | G99: No | H99: Si | I99: Si | L99: 1 | M99: 1 | N99: 5 | O99: 5 | P99: 20
A100: 110505020 | B100: FLETES | C100: activ | D100: BS | E100: PS | F100: Si | G100: No | H100: Si | I100: Si | L100: 1 | M100: 1 | N100: 5 | O100: 5 | P100: 30
A101: 110505030 | B101: DERECHOS DE IMPORTACIÓN | C101: activ | D101: BS | E101: PS | F101: Si | G101: No | H101: Si | I101: Si | L101: 1 | M101: 1 | N101: 5 | O101: 5 | P101: 50
A102: 110505050 | B102: SEGUROS IMPORTACIONES | C102: activ | D102: BS | E102: PS | F102: Si | G102: No | H102: Si | I102: Si | L102: 1 | M102: 1 | N102: 5 | O102: 5 | P102: 80
A103: 110505080 | B103: VARIOS | C103: activ | D103: BS | E103: PS | F103: Si | G103: No | H103: Si | I103: Si | L103: 1 | M103: 1 | N103: 5 | O103: 5 | P103: 85
A104: 110505085 | B104: GARANTIAS | C104: activ | D104: BS | E104: PS | F104: Si | G104: No | H104: Si | I104: Si | L104: 1 | M104: 1 | N104: 5 | O104: 5 | P104: 90
A105: 110505090 | B105: GASTOS CCIO EXT A RENDIR | C105: activ | D105: BS | E105: PS | F105: Si | G105: No | H105: Si | I105: Si | L105: 1 | M105: 1 | N105: 5 | O105: 5 | P105: 100
A106: 110505100 | B106: GASTOS IMPO A RENDIR | C106: activ | D106: BS | E106: PS | F106: Si | G106: No | H106: Si | I106: Si | L106: 1 | M106: 1 | N106: 5 | O106: 5 | P106: 300
A107: 110505300 | B107: MERCADERIA EN TRANSITO | C107: activ | D107: BS | E107: PS | F107: Si | G107: No | H107: Si | I107: Si | L107: 1 | M107: 1 | N107: 5 | O107: 15
...
